fishersapi/__init__.py
fishersapi/catcorr.py
fishersapi/fisher_numba.py
fishersapi/fishersapi.py
fishersapi/version.py
fishersapi/tests/__init__.py
fishersapi/tests/test_catcorr.py
fishersapi/tests/test_fishersapi.py
fishersapi-1.0.dist-info/LICENSE
fishersapi-1.0.dist-info/METADATA
fishersapi-1.0.dist-info/WHEEL
fishersapi-1.0.dist-info/top_level.txt
fishersapi-1.0.dist-info/RECORD
