Metadata-Version: 2.1
Name: fishersapi
Version: 1.0
Summary: fishersapi: An API for applying a fast Fisher's Exact Test to variable pairs in pandas DataFrames
Home-page: http://github.com/agartland/fishersapi
Download-URL: 
Author: Andrew Fiore-Gartland
Author-email: agartlan@fredhutch.org
Maintainer: Andrew Fiore-Gartland
Maintainer-email: agartlan@fredhutch.org
License: MIT
Platform: OS Independent
Classifier: Development Status :: 3 - Alpha
Classifier: Environment :: Console
Classifier: Intended Audience :: Science/Research
Classifier: License :: OSI Approved :: MIT License
Classifier: Operating System :: OS Independent
Classifier: Programming Language :: Python
Classifier: Topic :: Scientific/Engineering
Requires: numpy
Requires: scipy
Requires: pandas
Requires: statsmodels
License-File: LICENSE
Requires-Dist: numpy
Requires-Dist: pandas
Requires-Dist: scipy
Requires-Dist: statsmodels
